y_not_finance/__init__.py
y_not_finance/constituents/__init__.py
y_not_finance/constituents/client.py
y_not_finance/constituents/config.py
y_not_finance/constituents/utils.py
y_not_finance/constituents/scrapers/__init__.py
y_not_finance/constituents/scrapers/stock_analysis.py
y_not_finance/constituents/scrapers/tsx.py
y_not_finance/prices/__init__.py
y_not_finance/prices/client.py
y_not_finance/prices/constants.py
y_not_finance/prices/fetcher.py
y_not_finance/prices/parser.py
y_not_finance/prices/processor.py
y_not_finance/prices/utils.py
y_not_finance-1.0.0.dist-info/LICENSE
y_not_finance-1.0.0.dist-info/METADATA
y_not_finance-1.0.0.dist-info/WHEEL
y_not_finance-1.0.0.dist-info/top_level.txt
y_not_finance-1.0.0.dist-info/RECORD
