Metadata-Version: 2.1
Name: y_not_finance
Version: 1.0.0
Summary: Financial data library for prices and index constituents
Requires-Python: >=3.8
License-File: LICENSE
Requires-Dist: numpy
Requires-Dist: pandas
Requires-Dist: requests
